template_nn/__init__.py
template_nn/args_val.py
template_nn/keys.json
template_nn/retrieve_keys.py
template_nn/networks/__init__.py
template_nn/networks/base_nn.py
template_nn/networks/cml.py
template_nn/networks/cnn.py
template_nn/networks/fnn.py
template_nn-0.2.3.dist-info/licenses/LICENSE
template_nn-0.2.3.dist-info/METADATA
template_nn-0.2.3.dist-info/WHEEL
template_nn-0.2.3.dist-info/top_level.txt
template_nn-0.2.3.dist-info/RECORD
