Metadata-Version: 2.4
Name: template-nn
Version: 0.2.3
Summary: A neural network model architecture template
Author-email: Gabriel Choong Ge Liang <gabrielchoonggeliang@gmail.com>
License: MIT
Project-URL: Homepage, https://github.com/gabrielchoong/template-nn
Project-URL: Issues, https://github.com/gabrielchoong/template-nn/issues
Classifier: Programming Language :: Python :: 3
Classifier: License :: OSI Approved :: MIT License
Classifier: Operating System :: OS Independent
Requires-Python: >=3.10
License-File: LICENSE
Requires-Dist: torch>=2.6.0
Requires-Dist: numpy>=1.18.0
Provides-Extra: dev
Requires-Dist: pytest>=8.3.4; extra == "dev"
Requires-Dist: ruff; extra == "dev"
Requires-Dist: uv; extra == "dev"
Requires-Dist: pip-tools; extra == "dev"
Dynamic: license-file
